13_if/my_n_and.vhd
library IEEE;
use IEEE.std_logic_1164.all;

entity my_n_and is
	port(
		a   : in  std_logic_vector(1 downto 0);
		sel : in  std_logic;
		y   : out std_logic
	);
end my_n_and;

architecture basic of my_n_and is

begin

	y <= a(1) and a(0) when sel='1' else a(1) nand a(0);

end basic;

13_if/tb_my_n_and.vhd
library IEEE;
use IEEE.std_logic_1164.all;

entity tb_my_n_and is
--vazio
end tb_my_n_and;

architecture tb1 of tb_my_n_and is

--DUT
component my_n_and is
	port(
		a   : in  std_logic_vector(1 downto 0);
		sel : in  std_logic;
		y   : out std_logic
	);
end component;

signal a_in   : std_logic_vector(1 downto 0);
signal sel_in : std_logic;
signal y_out  : std_logic;

begin

DUT: my_n_and port map(
			a   => a_in,
			sel => sel_in,
			y   => y_out
		);

process
begin

	a_in   <= "XX";
	sel_in <= '0';
	wait for 1 ns;
	
	a_in   <= "XX";
	sel_in <= '1';
	wait for 1 ns;
	
	a_in   <= "00";
	sel_in <= '0';
	wait for 1 ns;
	
	a_in   <= "00";
	sel_in <= '1';
	wait for 1 ns;
	
	a_in   <= "01";
	sel_in <= '0';
	wait for 1 ns;
	
	a_in   <= "01";
	sel_in <= '1';
	wait for 1 ns;
	
	a_in   <= "10";
	sel_in <= '0';
	wait for 1 ns;
	
	a_in   <= "10";
	sel_in <= '1';
	wait for 1 ns;
	
	a_in   <= "11";
	sel_in <= '0';
	wait for 1 ns;
	
	a_in   <= "11";
	sel_in <= '1';
	wait for 1 ns;
	
	a_in   <= "XX";
	sel_in <= '0';
	wait for 1 ns;
	
	a_in   <= "XX";
	sel_in <= '1';
	wait;

end process;

end tb1;

13_if/n_and.vcd
$date
  Thu Aug 19 02:07:07 2021
$end
$version
  GHDL v0
$end
$timescale
  1 fs
$end
$scope module standard $end
$upscope $end
$scope module std_logic_1164 $end
$upscope $end
$scope module tb_my_n_and $end
$var reg 2 ! a_in[1:0] $end
$var reg 1 " sel_in $end
$var reg 1 # y_out $end
$scope module dut $end
$var reg 2 $ a[1:0] $end
$var reg 1 % sel $end
$var reg 1 & y $end
$upscope $end
$upscope $end
$enddefinitions $end
#0
bXX !
0"
X#
bXX $
0%
X&
#1000000
1"
1%
#2000000
b00 !
0"
1#
b00 $
0%
1&
#3000000
1"
0#
1%
0&
#4000000
b01 !
0"
1#
b01 $
0%
1&
#5000000
1"
0#
1%
0&
#6000000
b10 !
0"
1#
b10 $
0%
1&
#7000000
1"
0#
1%
0&
#8000000
b11 !
0"
b11 $
0%
#9000000
1"
1#
1%
1&
#10000000
bXX !
0"
X#
bXX $
0%
X&
#11000000
1"
1%
