14_logic/my_logic.vhd
library IEEE;
use IEEE.std_logic_1164.all;

entity my_logic is
	port(
		a   : in  std_logic_vector(1 downto 0);
		sel : in  std_logic_vector(2 downto 0);
		y   : out std_logic
	);
end my_logic;

architecture basic of my_logic is

begin

	y <=	(a(1) and  a(0))	when sel="000" else
		(a(1) nand a(0))	when sel="001" else
		(a(1) or   a(0))	when sel="010" else
		(a(1) nor  a(0))	when sel="011" else
		(a(1) xor  a(0))	when sel="100" else
		(a(1) xnor a(0))	when sel="101" else
		'Z' 		 	when sel="110" else
		'Z' 		 	when sel="111";

end basic;

14_logic/tb_my_logic.vhd
library IEEE;
use IEEE.std_logic_1164.all;

entity tb_my_logic is
--vazio
end tb_my_logic;

architecture tb1 of tb_my_logic is

--DUT
component my_logic is
	port(
		a   : in  std_logic_vector(1 downto 0);
		sel : in  std_logic_vector(2 downto 0);
		y   : out std_logic
	);
end component;

signal a_in   : std_logic_vector(1 downto 0);
signal sel_in : std_logic_vector(2 downto 0);
signal y_in   : std_logic;

begin

DUT: my_logic port map(
			a   => a_in,
			sel => sel_in,
			y   => y_in
		);
		
process
begin

	a_in   <= "00";
	sel_in <= "000";
	wait for 1 ns;
	
	a_in   <= "01";
	sel_in <= "000";
	wait for 1 ns;
	
	a_in   <= "10";
	sel_in <= "000";
	wait for 1 ns;
	
	a_in   <= "11";
	sel_in <= "000";
	wait for 1 ns;
	
	a_in   <= "00";
	sel_in <= "001";
	wait for 1 ns;
	
	a_in   <= "01";
	sel_in <= "001";
	wait for 1 ns;
	
	a_in   <= "10";
	sel_in <= "001";
	wait for 1 ns;
	
	a_in   <= "11";
	sel_in <= "001";
	wait for 1 ns;
	
	a_in   <= "00";
	sel_in <= "010";
	wait for 1 ns;
	
	a_in   <= "01";
	sel_in <= "010";
	wait for 1 ns;
	
	a_in   <= "10";
	sel_in <= "010";
	wait for 1 ns;
	
	a_in   <= "11";
	sel_in <= "010";
	wait for 1 ns;
	
	a_in   <= "00";
	sel_in <= "011";
	wait for 1 ns;
	
	a_in   <= "01";
	sel_in <= "011";
	wait for 1 ns;
	
	a_in   <= "10";
	sel_in <= "011";
	wait for 1 ns;
	
	a_in   <= "11";
	sel_in <= "011";
	wait for 1 ns;
	
	a_in   <= "00";
	sel_in <= "100";
	wait for 1 ns;
	
	a_in   <= "01";
	sel_in <= "100";
	wait for 1 ns;
	
	a_in   <= "10";
	sel_in <= "100";
	wait for 1 ns;
	
	a_in   <= "11";
	sel_in <= "100";
	wait for 1 ns;
	
	a_in   <= "00";
	sel_in <= "101";
	wait for 1 ns;
	
	a_in   <= "01";
	sel_in <= "101";
	wait for 1 ns;
	
	a_in   <= "10";
	sel_in <= "101";
	wait for 1 ns;
	
	a_in   <= "11";
	sel_in <= "101";
	wait for 1 ns;
	
	a_in   <= "00";
	sel_in <= "110";
	wait for 1 ns;
	
	a_in   <= "01";
	sel_in <= "110";
	wait for 1 ns;
	
	a_in   <= "10";
	sel_in <= "110";
	wait for 1 ns;
	
	a_in   <= "11";
	sel_in <= "110";
	wait for 1 ns;
	
	a_in   <= "00";
	sel_in <= "111";
	wait for 1 ns;
	
	a_in   <= "01";
	sel_in <= "111";
	wait for 1 ns;
	
	a_in   <= "10";
	sel_in <= "111";
	wait for 1 ns;
	
	a_in   <= "11";
	sel_in <= "111";
	wait;

end process;

end tb1;

14_logic/my_logic.vcd
$date
  Thu Aug 19 02:34:56 2021
$end
$version
  GHDL v0
$end
$timescale
  1 fs
$end
$scope module standard $end
$upscope $end
$scope module std_logic_1164 $end
$upscope $end
$scope module tb_my_logic $end
$var reg 2 ! a_in[1:0] $end
$var reg 3 " sel_in[2:0] $end
$var reg 1 # y_in $end
$scope module dut $end
$var reg 2 $ a[1:0] $end
$var reg 3 % sel[2:0] $end
$var reg 1 & y $end
$upscope $end
$upscope $end
$enddefinitions $end
#0
b00 !
b000 "
0#
b00 $
b000 %
0&
#1000000
b01 !
b01 $
#2000000
b10 !
b10 $
#3000000
b11 !
1#
b11 $
1&
#4000000
b00 !
b001 "
b00 $
b001 %
#5000000
b01 !
b01 $
#6000000
b10 !
b10 $
#7000000
b11 !
0#
b11 $
0&
#8000000
b00 !
b010 "
b00 $
b010 %
#9000000
b01 !
1#
b01 $
1&
#10000000
b10 !
b10 $
#11000000
b11 !
b11 $
#12000000
b00 !
b011 "
b00 $
b011 %
#13000000
b01 !
0#
b01 $
0&
#14000000
b10 !
b10 $
#15000000
b11 !
b11 $
#16000000
b00 !
b100 "
b00 $
b100 %
#17000000
b01 !
1#
b01 $
1&
#18000000
b10 !
b10 $
#19000000
b11 !
0#
b11 $
0&
#20000000
b00 !
b101 "
1#
b00 $
b101 %
1&
#21000000
b01 !
0#
b01 $
0&
#22000000
b10 !
b10 $
#23000000
b11 !
1#
b11 $
1&
#24000000
b00 !
b110 "
Z#
b00 $
b110 %
Z&
#25000000
b01 !
b01 $
#26000000
b10 !
b10 $
#27000000
b11 !
b11 $
#28000000
b00 !
b111 "
b00 $
b111 %
#29000000
b01 !
b01 $
#30000000
b10 !
b10 $
#31000000
b11 !
b11 $
